Iga_Comp_Info/__init__.py
Iga_Comp_Info/info.py
Iga_Comp_Info-0.1.0.dist-info/METADATA
Iga_Comp_Info-0.1.0.dist-info/WHEEL
Iga_Comp_Info-0.1.0.dist-info/top_level.txt
Iga_Comp_Info-0.1.0.dist-info/RECORD
