Metadata-Version: 2.1
Name: Iga_Comp_Info
Version: 0.1.0
Summary: Библиотека для вывода системной информации о компьютере
Author: IGA-PRO (admin-iga)
Classifier: Programming Language :: Python :: 3
Classifier: Operating System :: OS Independent
Requires-Dist: psutil
